vibemath/__init__.py
vibemath/core.py
vibemath-0.1.0.dist-info/licenses/LICENSE
vibemath-0.1.0.dist-info/METADATA
vibemath-0.1.0.dist-info/WHEEL
vibemath-0.1.0.dist-info/top_level.txt
vibemath-0.1.0.dist-info/RECORD
