Metadata-Version: 2.4
Name: vibemath
Version: 0.1.0
Summary: Python package that uses GPT to evaluate mathematical expressions
Home-page: https://github.com/yemeen/vibemath
Author: yemeen
Author-email: yemeen <your.email@example.com>
License: MIT
Project-URL: Homepage, https://github.com/yemeen/vibemath
Project-URL: Bug Tracker, https://github.com/yemeen/vibemath/issues
Project-URL: Documentation, https://github.com/yemeen/vibemath#readme
Keywords: math,gpt,ai,mathematics,evaluation,openai
Classifier: Development Status :: 3 - Alpha
Classifier: Intended Audience :: Developers
Classifier: Topic :: Scientific/Engineering :: Mathematics
Classifier: License :: OSI Approved :: MIT License
Classifier: Programming Language :: Python :: 3
Classifier: Programming Language :: Python :: 3.8
Classifier: Programming Language :: Python :: 3.9
Classifier: Programming Language :: Python :: 3.10
Classifier: Programming Language :: Python :: 3.11
Classifier: Programming Language :: Python :: 3.12
Classifier: Operating System :: OS Independent
Requires-Python: >=3.8
License-File: LICENSE
Requires-Dist: openai>=1.0.0
Requires-Dist: numpy>=1.20.0
Requires-Dist: python-dotenv>=1.0.0
Provides-Extra: dev
Requires-Dist: pytest>=7.0.0; extra == "dev"
Requires-Dist: pytest-cov>=4.0.0; extra == "dev"
Requires-Dist: black>=23.0.0; extra == "dev"
Requires-Dist: ruff>=0.1.0; extra == "dev"
Requires-Dist: mypy>=1.0.0; extra == "dev"
Requires-Dist: twine>=4.0.0; extra == "dev"
Requires-Dist: build>=0.10.0; extra == "dev"
Dynamic: author
Dynamic: home-page
Dynamic: license-file
Dynamic: requires-python
